.gitignore
LICENSE
MANIFEST.in
README.MD
TODO
setup.py
tox.ini
docs/sphinx/build/man/es-tools.1
docs/sphinx/build/man/es.1
docs/sphinx/build/man/esd.1
easyshare/__init__.py
easyshare/args.py
easyshare/auth.py
easyshare/common.py
easyshare/conf.py
easyshare/endpoint.py
easyshare/logging.py
easyshare/settings.py
easyshare/sockets.py
easyshare/ssl.py
easyshare/streams.py
easyshare/styling.py
easyshare/timer.py
easyshare/tracing.py
easyshare/tree.py
easyshare.egg-info/PKG-INFO
easyshare.egg-info/SOURCES.txt
easyshare.egg-info/dependency_links.txt
easyshare.egg-info/entry_points.txt
easyshare.egg-info/requires.txt
easyshare.egg-info/top_level.txt
easyshare/commands/__init__.py
easyshare/commands/commands.py
easyshare/commands/es.py
easyshare/commands/esd.py
easyshare/commands/estools.py
easyshare/consts/__init__.py
easyshare/consts/ansi.py
easyshare/consts/net.py
easyshare/consts/os.py
easyshare/consts/units.py
easyshare/devtests/__init__.py
easyshare/devtests/args.py
easyshare/devtests/auth.py
easyshare/devtests/cert.py
easyshare/devtests/cmd2test.py
easyshare/devtests/colors.py
easyshare/devtests/decdepth.py
easyshare/devtests/decorators.py
easyshare/devtests/esnopyro.py
easyshare/devtests/esnopyrorexec.py
easyshare/devtests/inspect.py
easyshare/devtests/md5.py
easyshare/devtests/path.py
easyshare/devtests/pty.py
easyshare/devtests/pty2.py
easyshare/devtests/ptyproc.py
easyshare/devtests/pyroc.py
easyshare/devtests/pyroc5.py
easyshare/devtests/pyroc5async.py
easyshare/devtests/pyros.py
easyshare/devtests/pyros5.py
easyshare/devtests/pyros5async.py
easyshare/devtests/rl.py
easyshare/devtests/sh.py
easyshare/devtests/sslclient.py
easyshare/devtests/sslclientpro.py
easyshare/devtests/sslserver.py
easyshare/devtests/sslserverpro.py
easyshare/devtests/stdin.py
easyshare/devtests/sync.py
easyshare/devtests/tcpclient.py
easyshare/devtests/tcpserver.py
easyshare/devtests/test.py
easyshare/devtests/udpclient.py
easyshare/devtests/udpserver.py
easyshare/devtests/walk.py
easyshare/es/__init__.py
easyshare/es/__main__.py
easyshare/es/client.py
easyshare/es/common.py
easyshare/es/connection.py
easyshare/es/discover.py
easyshare/es/errors.py
easyshare/es/shell.py
