Metadata-Version: 2.1
Name: easyshare
Version: 0.15
Summary: Client-Server command line application for share files, similar to FTP but more powerful; written in Python 3.6+
Home-page: https://github.com/Docheinstein/easyshare
Author: Stefano Dottore
Author-email: docheinstein@gmail.com
License: MIT
Keywords: easyshare
Platform: UNKNOWN
Requires-Python: >=3.6
